konfigurator/__init__.py
konfigurator/utils.py
tests/base_config.py
tests/config.py
tests/script.py
tests/test_config_parsing.py
tests/test_instantiation.py
konfigurator-0.2.1.dist-info/METADATA
konfigurator-0.2.1.dist-info/WHEEL
konfigurator-0.2.1.dist-info/top_level.txt
konfigurator-0.2.1.dist-info/RECORD
