Metadata-Version: 2.4
Name: konfigurator
Version: 0.2.1
Summary: A a simple python configuration management and object instantiation tool
Author-email: Maxim Dolgov <maxim.dolgov@hs-pforzheim.de>
License: MIT
Project-URL: Homepage, https://github.com/isealab/konfigurator
Keywords: config
Classifier: Development Status :: 3 - Alpha
Classifier: Intended Audience :: Developers
Classifier: Intended Audience :: Science/Research
Classifier: License :: OSI Approved :: MIT License
Classifier: Programming Language :: Python :: 3
Classifier: Programming Language :: Python :: 3.10
Classifier: Topic :: Software Development :: Libraries :: Python Modules
Requires-Python: >=3.10
Requires-Dist: ml_collections==1.1.0
Provides-Extra: dev
Requires-Dist: pre-commit==4.2.0; extra == "dev"
Requires-Dist: build; extra == "dev"
Requires-Dist: twine; extra == "dev"
Provides-Extra: test
Requires-Dist: pytest==8.4.1; extra == "test"
